[{"contest_id":"abc124","epoch_second":1555158304,"execution_time":1,"id":4949457,"language":"C++14 (GCC 5.4.1)","length":198,"point":100.0,"problem_id":"abc124_a","result":"AC","user_id":"wogu"}
,{"contest_id":"abc125","epoch_second":1556372147,"execution_time":1,"id":5161748,"language":"C++14 (GCC 5.4.1)","length":164,"point":100.0,"problem_id":"abc125_a","result":"AC","user_id":"wogu"}
,{"contest_id":"abc127","epoch_second":1558786139,"execution_time":1,"id":5593550,"language":"C++14 (GCC 5.4.1)","length":208,"point":100.0,"problem_id":"abc127_a","result":"AC","user_id":"wogu"}
,{"contest_id":"abc127","epoch_second":1558786762,"execution_time":1,"id":5598695,"language":"C++14 (GCC 5.4.1)","length":549,"point":200.0,"problem_id":"abc127_b","result":"AC","user_id":"wogu"}
,{"contest_id":"abc127","epoch_second":1558788827,"execution_time":"","id":5607250,"language":"C++14 (GCC 5.4.1)","length":504,"point":0.0,"problem_id":"abc127_c","result":"TLE","user_id":"wogu"}
,{"contest_id":"abc127","epoch_second":1558789092,"execution_time":"","id":5608138,"language":"C++14 (GCC 5.4.1)","length":524,"point":0.0,"problem_id":"abc127_c","result":"TLE","user_id":"wogu"}
,{"contest_id":"abc127","epoch_second":1558789944,"execution_time":"","id":5610797,"language":"C++14 (GCC 5.4.1)","length":657,"point":0.0,"problem_id":"abc127_c","result":"TLE","user_id":"wogu"}
,{"contest_id":"abc137","epoch_second":1565438839,"execution_time":1,"id":6807101,"language":"C++14 (GCC 5.4.1)","length":320,"point":100.0,"problem_id":"abc137_a","result":"AC","user_id":"wogu"}
,{"contest_id":"abc137","epoch_second":1565439578,"execution_time":1,"id":6812393,"language":"C++14 (GCC 5.4.1)","length":209,"point":200.0,"problem_id":"abc137_b","result":"AC","user_id":"wogu"}
,{"contest_id":"abc137","epoch_second":1565445013,"execution_time":"","id":6832246,"language":"C++14 (GCC 5.4.1)","length":433,"point":0.0,"problem_id":"abc137_c","result":"TLE","user_id":"wogu"}
,{"contest_id":"abc136","epoch_second":1565447646,"execution_time":1,"id":6834576,"language":"C++14 (GCC 5.4.1)","length":188,"point":100.0,"problem_id":"abc136_a","result":"AC","user_id":"wogu"}
,{"contest_id":"abc136","epoch_second":1565448552,"execution_time":1,"id":6835123,"language":"C++14 (GCC 5.4.1)","length":330,"point":200.0,"problem_id":"abc136_b","result":"AC","user_id":"wogu"}
,{"contest_id":"abc136","epoch_second":1565862616,"execution_time":44,"id":6919642,"language":"C++14 (GCC 5.4.1)","length":544,"point":0.0,"problem_id":"abc136_c","result":"WA","user_id":"wogu"}
,{"contest_id":"abc136","epoch_second":1565862766,"execution_time":44,"id":6919691,"language":"C++14 (GCC 5.4.1)","length":683,"point":0.0,"problem_id":"abc136_c","result":"WA","user_id":"wogu"}
,{"contest_id":"abc136","epoch_second":1565863604,"execution_time":44,"id":6919937,"language":"C++14 (GCC 5.4.1)","length":706,"point":0.0,"problem_id":"abc136_c","result":"WA","user_id":"wogu"}
,{"contest_id":"abc136","epoch_second":1565863752,"execution_time":44,"id":6919971,"language":"C++14 (GCC 5.4.1)","length":795,"point":0.0,"problem_id":"abc136_c","result":"WA","user_id":"wogu"}
,{"contest_id":"abc136","epoch_second":1565890839,"execution_time":45,"id":6926961,"language":"C++14 (GCC 5.4.1)","length":909,"point":300.0,"problem_id":"abc136_c","result":"AC","user_id":"wogu"}
,{"contest_id":"abc136","epoch_second":1566045188,"execution_time":13,"id":6956767,"language":"C++14 (GCC 5.4.1)","length":2134,"point":0.0,"problem_id":"abc136_d","result":"WA","user_id":"wogu"}
,{"contest_id":"abc136","epoch_second":1566045288,"execution_time":16,"id":6956879,"language":"C++14 (GCC 5.4.1)","length":2156,"point":400.0,"problem_id":"abc136_d","result":"AC","user_id":"wogu"}
,{"contest_id":"abc117","epoch_second":1566067061,"execution_time":1,"id":6967698,"language":"C++14 (GCC 5.4.1)","length":361,"point":200.0,"problem_id":"abc117_b","result":"AC","user_id":"wogu"}
,{"contest_id":"abc117","epoch_second":1566067597,"execution_time":1,"id":6967754,"language":"C++14 (GCC 5.4.1)","length":183,"point":100.0,"problem_id":"abc117_a","result":"AC","user_id":"wogu"}
,{"contest_id":"abc117","epoch_second":1566068833,"execution_time":"","id":6967871,"language":"C++14 (GCC 5.4.1)","length":401,"point":0.0,"problem_id":"abc117_d","result":"TLE","user_id":"wogu"}
,{"contest_id":"abc117","epoch_second":1566071295,"execution_time":40,"id":6968065,"language":"C++14 (GCC 5.4.1)","length":590,"point":300.0,"problem_id":"abc117_c","result":"AC","user_id":"wogu"}
,{"contest_id":"abc135","epoch_second":1566072727,"execution_time":584,"id":6968143,"language":"C++14 (GCC 5.4.1)","length":474,"point":100.0,"problem_id":"abc135_a","result":"AC","user_id":"wogu"}
,{"contest_id":"abc135","epoch_second":1566073371,"execution_time":1,"id":6968181,"language":"C++14 (GCC 5.4.1)","length":339,"point":200.0,"problem_id":"abc135_b","result":"AC","user_id":"wogu"}
,{"contest_id":"abc137","epoch_second":1566114187,"execution_time":"","id":6975284,"language":"C++14 (GCC 5.4.1)","length":392,"point":0.0,"problem_id":"abc137_c","result":"TLE","user_id":"wogu"}
,{"contest_id":"abc135","epoch_second":1566118017,"execution_time":97,"id":6976565,"language":"C++14 (GCC 5.4.1)","length":944,"point":300.0,"problem_id":"abc135_c","result":"AC","user_id":"wogu"}
,{"contest_id":"abc134","epoch_second":1566118259,"execution_time":1,"id":6976646,"language":"C++14 (GCC 5.4.1)","length":113,"point":100.0,"problem_id":"abc134_a","result":"AC","user_id":"wogu"}
,{"contest_id":"abc134","epoch_second":1566118676,"execution_time":1,"id":6976789,"language":"C++14 (GCC 5.4.1)","length":232,"point":200.0,"problem_id":"abc134_b","result":"AC","user_id":"wogu"}
,{"contest_id":"abc134","epoch_second":1566119226,"execution_time":"","id":6976985,"language":"C++14 (GCC 5.4.1)","length":384,"point":0.0,"problem_id":"abc134_c","result":"TLE","user_id":"wogu"}
,{"contest_id":"abc134","epoch_second":1566119885,"execution_time":367,"id":6977178,"language":"C++14 (GCC 5.4.1)","length":478,"point":300.0,"problem_id":"abc134_c","result":"AC","user_id":"wogu"}
,{"contest_id":"abc127","epoch_second":1566120905,"execution_time":57,"id":6977513,"language":"C++14 (GCC 5.4.1)","length":494,"point":300.0,"problem_id":"abc127_c","result":"AC","user_id":"wogu"}
,{"contest_id":"abc125","epoch_second":1566121368,"execution_time":1,"id":6977661,"language":"C++14 (GCC 5.4.1)","length":398,"point":200.0,"problem_id":"abc125_b","result":"AC","user_id":"wogu"}
,{"contest_id":"abc138","epoch_second":1566129780,"execution_time":1,"id":6983525,"language":"C++14 (GCC 5.4.1)","length":191,"point":100.0,"problem_id":"abc138_a","result":"AC","user_id":"wogu"}
,{"contest_id":"abc138","epoch_second":1566130076,"execution_time":1,"id":6987932,"language":"C++14 (GCC 5.4.1)","length":270,"point":200.0,"problem_id":"abc138_b","result":"AC","user_id":"wogu"}
,{"contest_id":"abc138","epoch_second":1566131111,"execution_time":3,"id":6995294,"language":"C++14 (GCC 5.4.1)","length":507,"point":300.0,"problem_id":"abc138_c","result":"AC","user_id":"wogu"}
,{"contest_id":"abc133","epoch_second":1566136646,"execution_time":1,"id":7010933,"language":"C++14 (GCC 5.4.1)","length":138,"point":100.0,"problem_id":"abc133_a","result":"AC","user_id":"wogu"}
,{"contest_id":"abc116","epoch_second":1566193079,"execution_time":1,"id":7021939,"language":"C++14 (GCC 5.4.1)","length":146,"point":100.0,"problem_id":"abc116_a","result":"AC","user_id":"wogu"}
,{"contest_id":"abc116","epoch_second":1566195334,"execution_time":1,"id":7022552,"language":"C++14 (GCC 5.4.1)","length":458,"point":200.0,"problem_id":"abc116_b","result":"AC","user_id":"wogu"}
,{"contest_id":"abc116","epoch_second":1566261034,"execution_time":1,"id":7036264,"language":"C++14 (GCC 5.4.1)","length":622,"point":0.0,"problem_id":"abc116_c","result":"WA","user_id":"wogu"}
,{"contest_id":"abc116","epoch_second":1566261162,"execution_time":1,"id":7036285,"language":"C++14 (GCC 5.4.1)","length":644,"point":0.0,"problem_id":"abc116_c","result":"WA","user_id":"wogu"}
,{"contest_id":"abc116","epoch_second":1566261412,"execution_time":"","id":7036313,"language":"C++14 (GCC 5.4.1)","length":663,"point":0.0,"problem_id":"abc116_c","result":"CE","user_id":"wogu"}
,{"contest_id":"abc116","epoch_second":1566261476,"execution_time":1,"id":7036323,"language":"C++14 (GCC 5.4.1)","length":663,"point":300.0,"problem_id":"abc116_c","result":"AC","user_id":"wogu"}
,{"contest_id":"abc132","epoch_second":1566270394,"execution_time":1,"id":7037797,"language":"C++14 (GCC 5.4.1)","length":259,"point":100.0,"problem_id":"abc132_a","result":"AC","user_id":"wogu"}
,{"contest_id":"abc132","epoch_second":1566271042,"execution_time":1,"id":7037907,"language":"C++14 (GCC 5.4.1)","length":356,"point":200.0,"problem_id":"abc132_b","result":"AC","user_id":"wogu"}
]