[{"contest_id":"abc021","epoch_second":1503559879,"execution_time":1,"id":1536006,"language":"C (GCC 5.4.1)","length":209,"point":100,"problem_id":"abc021_a","result":"AC","user_id":"moto"}
,{"contest_id":"abc021","epoch_second":1503562514,"execution_time":1,"id":1536076,"language":"C (GCC 5.4.1)","length":587,"point":100,"problem_id":"abc021_b","result":"AC","user_id":"moto"}
,{"contest_id":"abc021","epoch_second":1503594020,"execution_time":"","id":1536639,"language":"C (GCC 5.4.1)","length":1547,"point":0,"problem_id":"abc021_c","result":"TLE","user_id":"moto"}
,{"contest_id":"abc021","epoch_second":1503636330,"execution_time":"","id":1537013,"language":"C (GCC 5.4.1)","length":1381,"point":0,"problem_id":"abc021_c","result":"TLE","user_id":"moto"}
,{"contest_id":"abc045","epoch_second":1503640193,"execution_time":1,"id":1537118,"language":"C (GCC 5.4.1)","length":555,"point":0,"problem_id":"abc045_b","result":"WA","user_id":"moto"}
,{"contest_id":"abc045","epoch_second":1503640546,"execution_time":1,"id":1537136,"language":"C (GCC 5.4.1)","length":477,"point":200,"problem_id":"abc045_b","result":"AC","user_id":"moto"}
,{"contest_id":"abc036","epoch_second":1503643859,"execution_time":"","id":1537262,"language":"C (GCC 5.4.1)","length":682,"point":30,"problem_id":"abc036_c","result":"RE","user_id":"moto"}
,{"contest_id":"abc036","epoch_second":1503644122,"execution_time":"","id":1537280,"language":"C (GCC 5.4.1)","length":705,"point":30,"problem_id":"abc036_c","result":"RE","user_id":"moto"}
,{"contest_id":"abc036","epoch_second":1503644249,"execution_time":"","id":1537287,"language":"C (GCC 5.4.1)","length":741,"point":30,"problem_id":"abc036_c","result":"RE","user_id":"moto"}
,{"contest_id":"abc036","epoch_second":1503644340,"execution_time":"","id":1537294,"language":"C (GCC 5.4.1)","length":743,"point":30,"problem_id":"abc036_c","result":"RE","user_id":"moto"}
,{"contest_id":"abc032","epoch_second":1504502959,"execution_time":1,"id":1568111,"language":"C (GCC 5.4.1)","length":475,"point":100,"problem_id":"abc032_b","result":"AC","user_id":"moto"}
,{"contest_id":"abc047","epoch_second":1504505599,"execution_time":1,"id":1568249,"language":"C (GCC 5.4.1)","length":1371,"point":200,"problem_id":"abc047_b","result":"AC","user_id":"moto"}
,{"contest_id":"abc061","epoch_second":1504507900,"execution_time":2103,"id":1568360,"language":"C (GCC 5.4.1)","length":746,"point":0,"problem_id":"abc061_c","result":"WA","user_id":"moto"}
]